{
  "seo": {
    "title": "ลบพื้นหลังของรูปภาพอิสระ ○ ลบพื้นหลัง AI",
    "description": "ลบพื้นหลังภาพทันทีด้วยเครื่องมือ AI ของเราพลังงาน สมบูรณ์แบบสําหรับ e-commerce, โซเชียลมีเดีย, และการออกแบบ ไม่ต้องลงชื่อ ประมวลผลภาพในวินาทีด้วยผลลัพธ์คุณภาพมืออาชีพ",
    "keywords": "ลบพื้นหลัง, ลบพื้นหลัง, ลบพื้นหลัง AI, พื้นหลังแบบโปร่งแสง, ลบพื้นหลังแบบโปร่งใส, ลบพื้นหลังภาพ, พื้นหลังภาพถ่าย, ลบพื้นหลังแบบออนไลน์, ลบพื้นหลัง, ลบพื้นหลังแบบฉลาด, ลบพื้นหลังแบบมืออาชีพ, เอาออก, ลบพื้นหลังแบบใหญ่",
    "codinasion": "โคดินาชัน",
    "og_title": "พื้นหลังแบบอิสระ AI - ลบพื้นหลังภาพออกโดยทันที ○ เอาแผ่นออก",
    "og_description": "การถอดพื้นหลัง AI มืออาชีพในไม่กี่วินาที สมบูรณ์แบบสําหรับ e-commerce, โซเชียลมีเดีย, และโครงการสร้างสรรค์ เป็นอิสระ 100% และเน้นความเป็นส่วนตัว ถูกใช้โดยผู้สร้าง 1M+ ทั่วโลก"
  },
  "navbar": {
    "text_1": "เอาแผ่นออก BG",
    "text_2": "คุณสมบัติต่าง ๆ",
    "text_3": "ใช้ตัวพิมพ์เล็ก",
    "text_4": "ทบทวน",
    "text_5": "เริ่มได้"
  },
  "hero": {
    "text_1": "พื้นหลัง AI",
    "text_2": "ลบพื้นหลังของภาพ ทันที",
    "text_3": "การถอดพื้นหลัง AI มืออาชีพในไม่กี่วินาที สมบูรณ์แบบสําหรับ e-commerce, โซเชียลมีเดีย, และโครงการสร้างสรรค์ ไม่ต้องใช้ทักษะการออกแบบ",
    "text_4": "ลองให้ว่างเดี๋ยวนี้"
  },
  "component": {
    "text_1": "ลบพื้นหลังใน 3 ขั้นที่เรียบง่าย",
    "text_2": "อัปโหลด, ประมวลผล และดาวน์โหลดภาพของคุณด้วยพื้นหลังโปร่งใส",
    "text_3": "อัปโหลดภาพของคุณ",
    "text_4": "ลากและวาง หรือคลิกเพื่อเลือก",
    "text_5": "รองรับ JPG, PNG, WebP (Max 10 MB)",
    "text_6": "ดั้งเดิม",
    "text_7": "ประมวลผลแล้ว",
    "text_8": "AI กําลังลบพื้นหลัง",
    "text_9": "คลิกเพื่อดูผลลัพธ์",
    "text_10": "ลบพื้นหลัง",
    "text_11": "ดาวน์โหลด PNG",
    "text_12": "เริ่มทํางานใหม่",
    "text_13": "ข้อ แนะ สําหรับ ผล ดี ที่ สุด",
    "text_14": "ใช้ภาพต่าง ๆ ที่มีความแตกต่างระหว่างเนื้อเรื่องและหลัง (กรอบหน้าต่าง) ชัดเจน",
    "text_15": "หลีกเลี่ยงภาพขนาดเล็กหรือน้อย",
    "text_16": "ภาพสีดี ทํางานดีกว่าภาพมืด",
    "text_17": "ประมวลผลครั้งแรก รุ่น AI (50 MB)",
    "text_18": "การประมวลผลใช้เวลา 5-15 วินาที ขึ้นอยู่กับอุปกรณ์",
    "text_19": "ใช้ครั้งแรก: รุ่น AI จะดาวน์โหลดโดยอัตโนมัติ (50 MB, ครั้งเดียว). นั่นคือค่าใช้จ่ายของการผูกขาด"
  },
  "bmc": {
    "text_1": "เชื้อเพลิงนวัตกรรมของเรา",
    "text_2": "ชอบเครื่องมือนี้ไหม? ช่วย เรา ให้ มี กาแฟ แบบเสมือน จริง และ ช่วย เรา ปรับ ปรุง ให้ ดี ขึ้น!",
    "text_3": "ซื้อกาแฟ",
    "text_4": "ขอบคุณสําหรับการสนับสนุนเครื่องมือโอเพนซอร์ส"
  },
  "features": {
    "text_1": "คุณลักษณะ อัน ทรง พลัง สําหรับ ผล ที่ สมบูรณ์ พร้อม",
    "text_2": "เทคโนโลยี AI ขั้นสูง ตรงกับการออกแบบที่เป็นมิตรกับผู้ใช้ เพื่อส่งมอบพื้นหลังคุณภาพมืออาชีพ",
    "text_3": "ฟ้าแลบเร็ว",
    "text_4": "ประมวลผลภาพภายในเวลา 3 วินาที ด้วยอัลกอริทึม AI ที่ดีที่สุดของเรา",
    "text_5": "ส่วนตัว 100%",
    "text_6": "ภาพต่าง ๆ ของคุณถูกประมวลผลภายในเครื่อง และไม่เคยเก็บไว้ในเซิร์ฟเวอร์ของเรา",
    "text_7": "การ ทํา งาน ทั่ว โลก",
    "text_8": "โอปทิเมตสําหรับทุกภูมิภาคที่มีการสนับสนุนหลายภาษามาในไม่ช้า",
    "text_9": "คุณภาพสูง",
    "text_10": "รักษาคุณภาพของภาพไว้ โดยมีการตรวจจับขอบและการลดรอยหยัก",
    "text_11": "พรีซิชันที่สมบูรณ์แบบ",
    "text_12": "การตรวจจับขอบ AI ที่มีประสิทธิภาพจับผมที่ซับซ้อน ขนและรายละเอียดที่ดี",
    "text_13": "หลายรูปแบบ",
    "text_14": "ดาวน์โหลดใน PNG, JPG หรือเว็บพีที่มีพื้นหลังโปร่งใสหรือสี"
  },
  "use_cases": {
    "text_1": "สมบูรณ์แบบสําหรับทุกกรณี",
    "text_2": "จาก e-commerce ถึงโซเชียลมีเดีย ดูวิธีที่เครื่องมือของเราเปลี่ยนแปลงการไหลของงาน",
    "text_3": "แบบ E-commerce",
    "text_4": "ล้างภาพถ่ายผลิตภัณฑ์สําหรับร้านค้าออนไลน์",
    "text_5": "ภาพถ่าย",
    "text_6": "การแก้ไขภาพแบบมืออาชีพ",
    "text_7": "สื่อสังคม",
    "text_8": "โพสต์และเรื่องราว",
    "text_9": "การตลาด",
    "text_10": "สินทรัพย์การหาเสียงแบบมืออาชีพ"
  },
  "fun_facts": {
    "text_1": "ตัวเลขที่น่าตื่นตาตื่นใจ",
    "text_2": "ดูผลกระทบที่เรากําลังทําทั่วโลก",
    "text_3": "ประมวลผลภาพแล้ว",
    "text_4": "ประเทศ ที่ รับ ใช้",
    "text_5": "ความละเอียด",
    "text_6": "เวลาประมวลผลเฉลี่ย"
  },
  "historical_context": {
    "text_1": "วิวัฒนาการ ของ การ ขจัด ภูมิ หลัง",
    "text_2": "จากชั่วโมงการทํางานด้วยตนเองถึงผล AI ที่มีประสิทธิภาพทันที",
    "text_3": "เครื่องมือจัดการภาพถ่ายเอง อีra",
    "text_4": "ผู้ ออก แบบ ใช้ เวลา หลาย ชั่วโมง ใน การ เลือก และ ขจัด ภูมิ หลัง โดย ใช้ เครื่อง มือ ที่ ซับ ซ้อน",
    "text_5": "กึ่งอัตโนมัติ เครื่องมือ",
    "text_6": "ไม้ มนต์ และ เครื่อง มือ คล้าย ๆ กัน ทํา ให้ กระบวนการ นั้น เร็ว ขึ้น แต่ ยัง คง ต้อง ใช้ ความ ชํานาญ",
    "text_7": "การปฏิวัติ AI",
    "text_8": "อัลกอริทึม ใน การ เรียน รู้ ที่ ลึก ซึ้ง ใน ตอน นี้ สามารถ ขจัด ภูมิ หลัง ได้ ทันที พร้อม ด้วย ความ แม่นยํา เหนือ มนุษย์"
  },
  "testimonials": {
    "text_1": "ความ รัก ของ พระ ผู้ สร้าง ตลอด ทั่ว โลก",
    "text_2": "ดูที่ผู้ใช้ของเราพูด",
    "text_3": "ซา ราห์ เฉิน",
    "text_4": "เจ้าของ E-commerce",
    "text_5": "เครื่องมือนี้ช่วยฉันได้หลายร้อยชั่วโมง รูปสินค้าของผมดูเป็นมืออาชีพ และยอดขายของผมเพิ่มขึ้น 40%",
    "text_6": "มาร์ โค โร ดริ เกซ",
    "text_7": "ตัวจัดการสื่อสังคม",
    "text_8": "คุณภาพมันเหลือเชื่อ และมันเร็วมาก ฉันสามารถสร้างโพสต์ที่มีส่วนร่วมในนาทีแทนชั่วโมง",
    "text_9": "ไอชา พาเทล",
    "text_10": "โปรแกรมออกแบบอิสระ",
    "text_11": "ในฐานะคนที่ทํางานกับลูกค้าระหว่างประเทศ เครื่องมือนี้เปลี่ยนเกม ผลสมบูรณ์แบบทุกครั้ง!"
  },
  "cta": {
    "text_1": "พร้อมจะลบพื้นหลังเหมือนมืออาชีพหรือยัง",
    "text_2": "เข้าร่วมผู้ใช้กว่า 1 ล้านคนที่เชื่อถือเครื่องมือถอดพื้นหลัง AI ของเรา",
    "text_3": "เริ่มการเอาพื้นหลังออก"
  },
  "sponsor": {
    "text_1": "มา เป็น ผู้ รับ ใช้ ที่ โดด เด่น ของ เรา",
    "text_2": "รับเครื่องหมายถาวรบนเครื่องมือของเราที่ถูกใช้โดยล้านทั่วโลก",
    "text_3": "แค่ $100",
    "text_4": "ช่วงชีวิต",
    "text_5": "จํากัด แค่ 1 สไป ร์",
    "text_6": "สิ่ง ที่ คุณ ได้ รับ",
    "text_7": "โลโก้ของคุณแสดงอย่างชัดเจน",
    "text_8": "เชื่อมโยงไปยังเว็บไซต์ของคุณ",
    "text_9": "มี การ อ้าง ถึง ใน สื่อ สังคม",
    "text_10": "รับประกันตําแหน่งตลอดไป",
    "text_11": "สมบูรณ์แบบสําหรับ",
    "text_12": "บริษัทซาซ่าพุ่งเป้าไปที่ความคิดสร้างสรรค์",
    "text_13": "เครื่องมือออกแบบและบริการ",
    "text_14": "ธุรกิจถ่ายภาพ",
    "text_15": "แพลตฟอร์ม E-commerce",
    "text_16": "การอ้างสิทธิ์",
    "text_17": "ถึงผู้ใช้ 1M+ รายเดือน",
    "text_18": "มาครั้งแรก เสิร์ฟครั้งแรก"
  }
}
